CHANGELOG.md
wanna/__init__.py
wanna/cli/__init__.py
wanna/cli/__main__.py
wanna/cli/plugins/__init__.py
wanna/cli/plugins/base_plugin.py
wanna/cli/plugins/common_options.py
wanna/cli/plugins/job_plugin.py
wanna/cli/plugins/notebook_plugin.py
wanna/cli/plugins/pipeline_plugin.py
wanna/cli/plugins/runner.py
wanna/cli/plugins/tensorboard_plugin.py
wanna/cli/version.py
wanna/components/__init__.py
wanna/components/kubeflow/get_or_create_endpoint.py
wanna/components/kubeflow/upload_model_version.py
wanna/components/loader.py
wanna/core/__init__.py
wanna/core/deployment/__init__.py
wanna/core/deployment/artifacts_push.py
wanna/core/deployment/credentials.py
wanna/core/deployment/io.py
wanna/core/deployment/models.py
wanna/core/deployment/monitoring.py
wanna/core/deployment/vertex_connector.py
wanna/core/deployment/vertex_jobs.py
wanna/core/deployment/vertex_pipelines.py
wanna/core/deployment/vertex_scheduling.py
wanna/core/loggers/wanna_logger.py
wanna/core/models/__init__.py
wanna/core/models/base_instance.py
wanna/core/models/cloud_scheduler.py
wanna/core/models/docker.py
wanna/core/models/gcp_components.py
wanna/core/models/gcp_profile.py
wanna/core/models/notification_channel.py
wanna/core/models/pipeline.py
wanna/core/models/tensorboard.py
wanna/core/models/training_custom_job.py
wanna/core/models/wanna_config.py
wanna/core/models/wanna_project.py
wanna/core/models/workbench.py
wanna/core/services/__init__.py
wanna/core/services/base.py
wanna/core/services/docker.py
wanna/core/services/jobs.py
wanna/core/services/path_utils.py
wanna/core/services/pipeline.py
wanna/core/services/tensorboard.py
wanna/core/services/workbench.py
wanna/core/services/workbench_instance.py
wanna/core/templates/__init__.py
wanna/core/templates/notebook_startup_script.sh.j2
wanna/core/templates/notebook_template.Dockerfile
wanna/core/templates/scheduler_cloud_function.py
wanna/core/templates/scheduler_cloud_function_requirements.txt
wanna/core/templates/sla_cloud_function.py
wanna_ml-0.5.22.dist-info/LICENCE
wanna_ml-0.5.22.dist-info/METADATA
wanna_ml-0.5.22.dist-info/WHEEL
wanna_ml-0.5.22.dist-info/entry_points.txt
wanna_ml-0.5.22.dist-info/RECORD
