Metadata-Version: 2.1
Name: wanna-ml
Version: 0.5.22
Summary: CLI tool for managing ML projects on Vertex AI
Home-page: https://avast.github.io/wanna-ml
License: MIT
Keywords: mlops,vertex-ai,GCP,google-cloud-platform,machine-learning
Author: Joao Da Silva
Author-email: joao.dasilvacunha@gendigital.com
Requires-Python: >=3.10.0,<4.0
Classifier: Development Status :: 4 - Beta
Classifier: Intended Audience :: Developers
Classifier: Intended Audience :: Science/Research
Classifier: License :: OSI Approved :: MIT License
Classifier: Programming Language :: Python
Classifier: Programming Language :: Python :: 3
Classifier: Programming Language :: Python :: 3.10
Classifier: Programming Language :: Python :: 3.11
Classifier: Programming Language :: Python :: 3.12
Classifier: Programming Language :: Python :: 3.13
Classifier: Programming Language :: Python :: 3 :: Only
Classifier: Topic :: Scientific/Engineering
Classifier: Topic :: Scientific/Engineering :: Artificial Intelligence
Classifier: Typing :: Typed
Requires-Dist: Jinja2 (>=3.1.6,<4.0.0)
Requires-Dist: PyYAML (>=6.0.3,<7.0.0)
Requires-Dist: case-converter (>=1.2.0,<2.0.0)
Requires-Dist: cookiecutter (>=2.6.0,<3.0.0)
Requires-Dist: cron-validator (>=1.0.8,<2.0.0)
Requires-Dist: dirhash (>=0.5.0,<0.6.0)
Requires-Dist: email-validator (>=2.3.0,<3.0.0)
Requires-Dist: emoji (>=2.15.0,<3.0.0)
Requires-Dist: gcloud-config-helper (>=0.3.1,<0.4.0)
Requires-Dist: gitpython (>=3.1.45,<4.0.0)
Requires-Dist: google-cloud-aiplatform (>=1.121.0,<2.0.0)
Requires-Dist: google-cloud-build (>=3.33.0,<4.0.0)
Requires-Dist: google-cloud-compute (>=1.40.0,<2.0.0)
Requires-Dist: google-cloud-functions (>=1.20.4,<2.0.0)
Requires-Dist: google-cloud-logging (>=3.12.1,<4.0.0)
Requires-Dist: google-cloud-monitoring (>=2.28.0,<3.0.0)
Requires-Dist: google-cloud-notebooks (>=1.13.3,<2.0.0)
Requires-Dist: google-cloud-pubsub (>=2.31.1,<3.0.0)
Requires-Dist: google-cloud-scheduler (>=2.16.1,<3.0.0)
Requires-Dist: google-cloud-storage (>=2.19.0,<3.0.0)
Requires-Dist: halo (>=0.0.31,<0.0.32)
Requires-Dist: igittigitt (>=2.1.5,<3.0.0)
Requires-Dist: kfp (>=2.13.0,<3.0.0)
Requires-Dist: pathvalidate (>=3.3.1,<4.0.0)
Requires-Dist: pendulum (>=3.1.0,<4.0.0)
Requires-Dist: pydantic (>=2.12.3,<3.0.0)
Requires-Dist: python-on-whales (>=0.78.0,<0.79.0)
Requires-Dist: pyyaml-include (>=2.2,<3.0)
Requires-Dist: rich (>=14.2.0,<15.0.0)
Requires-Dist: smart-open[gcs] (>=7.3.1,<8.0.0)
Requires-Dist: treelib (>=1.8.0,<2.0.0)
Requires-Dist: typed-lazyimport (>=0.3.1,<0.4.0)
Requires-Dist: typer (>=0.20.0,<0.21.0)
Requires-Dist: waiting (>=1.5.0,<2.0.0)
Project-URL: Documentation, https://avast.github.io/wanna-ml
